python_scaffolding/__init__.py
python_scaffolding/content_one.py
python_scaffolding-0.1.dist-info/METADATA
python_scaffolding-0.1.dist-info/WHEEL
python_scaffolding-0.1.dist-info/top_level.txt
python_scaffolding-0.1.dist-info/RECORD
