Metadata-Version: 2.1
Name: python-scaffolding
Version: 0.1
Summary: Personal Python Scaffolding
Home-page: https://github.com/SamuelZhaoY/python-playground
Author: SamuelZhaoY
Author-email: samuel.zhao.yue@live.com
License: MIT
Platform: UNKNOWN
